CHANGELOG.txt
LICENCE.txt
MANIFEST.in
README.txt
setup.py
WordPressAutoPost.egg-info/PKG-INFO
WordPressAutoPost.egg-info/SOURCES.txt
WordPressAutoPost.egg-info/dependency_links.txt
WordPressAutoPost.egg-info/requires.txt
WordPressAutoPost.egg-info/top_level.txt
venv/Lib/site-packages/easy_install.py
venv/Lib/site-packages/filelock.py
venv/Lib/site-packages/requests_file.py
venv/Lib/site-packages/six.py
venv/Lib/site-packages/ProductDetailFinder-1.0.1-py3.8.egg-info/SOURCES.txt
venv/Lib/site-packages/ProductDetailFinder-1.0.1-py3.8.egg-info/dependency_links.txt
venv/Lib/site-packages/ProductDetailFinder-1.0.1-py3.8.egg-info/installed-files.txt
venv/Lib/site-packages/ProductDetailFinder-1.0.1-py3.8.egg-info/requires.txt
venv/Lib/site-packages/ProductDetailFinder-1.0.1-py3.8.egg-info/top_level.txt
venv/Lib/site-packages/_distutils_hack/__init__.py
venv/Lib/site-packages/_distutils_hack/override.py
venv/Lib/site-packages/affiliate_link_converter/__init__.py
venv/Lib/site-packages/affiliate_link_converter/__version__.py
venv/Lib/site-packages/affiliate_link_converter/common.py
venv/Lib/site-packages/affiliate_link_converter/constants.py
venv/Lib/site-packages/affiliate_link_converter/linkconverter.py
venv/Lib/site-packages/affiliatelinkconverter-1.0.6-py3.8.egg-info/SOURCES.txt
venv/Lib/site-packages/affiliatelinkconverter-1.0.6-py3.8.egg-info/dependency_links.txt
venv/Lib/site-packages/affiliatelinkconverter-1.0.6-py3.8.egg-info/installed-files.txt
venv/Lib/site-packages/affiliatelinkconverter-1.0.6-py3.8.egg-info/requires.txt
venv/Lib/site-packages/affiliatelinkconverter-1.0.6-py3.8.egg-info/top_level.txt
venv/Lib/site-packages/amazon/__init__.py
venv/Lib/site-packages/amazon/constant.py
venv/Lib/site-packages/amazon/exception.py
venv/Lib/site-packages/amazon/paapi.py
venv/Lib/site-packages/amazon/parse.py
venv/Lib/site-packages/amazon/tools.py
venv/Lib/site-packages/certifi/__init__.py
venv/Lib/site-packages/certifi/__main__.py
venv/Lib/site-packages/certifi/core.py
venv/Lib/site-packages/certifi-2020.12.5.dist-info/top_level.txt
venv/Lib/site-packages/chardet/__init__.py
venv/Lib/site-packages/chardet/big5freq.py
venv/Lib/site-packages/chardet/big5prober.py
venv/Lib/site-packages/chardet/chardistribution.py
venv/Lib/site-packages/chardet/charsetgroupprober.py
venv/Lib/site-packages/chardet/charsetprober.py
venv/Lib/site-packages/chardet/codingstatemachine.py
venv/Lib/site-packages/chardet/compat.py
venv/Lib/site-packages/chardet/cp949prober.py
venv/Lib/site-packages/chardet/enums.py
venv/Lib/site-packages/chardet/escprober.py
venv/Lib/site-packages/chardet/escsm.py
venv/Lib/site-packages/chardet/eucjpprober.py
venv/Lib/site-packages/chardet/euckrfreq.py
venv/Lib/site-packages/chardet/euckrprober.py
venv/Lib/site-packages/chardet/euctwfreq.py
venv/Lib/site-packages/chardet/euctwprober.py
venv/Lib/site-packages/chardet/gb2312freq.py
venv/Lib/site-packages/chardet/gb2312prober.py
venv/Lib/site-packages/chardet/hebrewprober.py
venv/Lib/site-packages/chardet/jisfreq.py
venv/Lib/site-packages/chardet/jpcntx.py
venv/Lib/site-packages/chardet-3.0.4.dist-info/entry_points.txt
venv/Lib/site-packages/chardet-3.0.4.dist-info/top_level.txt
venv/Lib/site-packages/click-7.1.2.dist-info/top_level.txt
venv/Lib/site-packages/filelock-3.0.12.dist-info/top_level.txt
venv/Lib/site-packages/furl-2.1.0.dist-info/LICENSE.txt
venv/Lib/site-packages/furl-2.1.0.dist-info/top_level.txt
venv/Lib/site-packages/idna-2.10.dist-info/top_level.txt
venv/Lib/site-packages/lxml-4.6.2.dist-info/LICENSE.txt
venv/Lib/site-packages/lxml-4.6.2.dist-info/LICENSES.txt
venv/Lib/site-packages/lxml-4.6.2.dist-info/top_level.txt
venv/Lib/site-packages/orderedmultidict-1.0.1.dist-info/LICENSE.txt
venv/Lib/site-packages/orderedmultidict-1.0.1.dist-info/top_level.txt
venv/Lib/site-packages/pip-20.3.1.dist-info/LICENSE.txt
venv/Lib/site-packages/pip-20.3.1.dist-info/entry_points.txt
venv/Lib/site-packages/pip-20.3.1.dist-info/top_level.txt
venv/Lib/site-packages/python_amazon_paapi-3.3.1.dist-info/top_level.txt
venv/Lib/site-packages/python_dateutil-2.8.1.dist-info/top_level.txt
venv/Lib/site-packages/python_wordpress_xmlrpc-2.3.dist-info/top_level.txt
venv/Lib/site-packages/requests-2.25.0.dist-info/top_level.txt
venv/Lib/site-packages/requests_file-1.5.1.dist-info/top_level.txt
venv/Lib/site-packages/setuptools-51.0.0.dist-info/dependency_links.txt
venv/Lib/site-packages/setuptools-51.0.0.dist-info/entry_points.txt
venv/Lib/site-packages/setuptools-51.0.0.dist-info/top_level.txt
venv/Lib/site-packages/six-1.15.0.dist-info/top_level.txt
venv/Lib/site-packages/tldextract-3.1.0.dist-info/entry_points.txt
venv/Lib/site-packages/tldextract-3.1.0.dist-info/top_level.txt
venv/Lib/site-packages/unshortenit-0.4.0.dist-info/entry_points.txt
venv/Lib/site-packages/unshortenit-0.4.0.dist-info/top_level.txt
venv/Lib/site-packages/urllib3-1.26.2.dist-info/LICENSE.txt
venv/Lib/site-packages/urllib3-1.26.2.dist-info/top_level.txt
